holeinfo/__init__.py
holeinfo/src.py
holeinfo-2.0.2.dist-info/LICENSE
holeinfo-2.0.2.dist-info/METADATA
holeinfo-2.0.2.dist-info/WHEEL
holeinfo-2.0.2.dist-info/entry_points.txt
holeinfo-2.0.2.dist-info/top_level.txt
holeinfo-2.0.2.dist-info/RECORD
